[
    {
        "execute": ">>> SCHEDULE (PST) >>>              Marie Vaunt 4pm, Alley Kay 5pm, Sian 6pm, Tyler Johnston: Into the Void 7pm, Idoru 8pm",
        "name": "settimes"
    },
    {
        "execute": ">>> TUES SCHEDULE (PST) >>>              Ex Libris 4pm, DJ SunrYse 6pm, Eric Allen 7pm, Tomas Otero 9pm",
        "name": "tuesday"
    },
    {
        "execute": ">>> WED SCHEDULE (PST) >>>              Melody's Enemy 4pm, Mullen 5pm, Michelle Sparks 6pm, Juheun 7pm, Jörgen 8pm",
        "name": "wednesday"
    },
    {
        "execute": ">>> THUR SCHEDULE (PST) >>>              Marie Vaunt 4pm, Alley Kay 5pm, Sian 6pm, Tyler Johnston: Into the Void 7pm, Idoru 8pm",
        "name": "thursday"
    },
    {
        "execute": "Nothing scheduled for this Friday!",
        "comment": ">>> FRI SCHEDULE (PST) >>>              Ex Libris: The Warmup 4pm-7pm",
        "name": "friday"
    },
    {
        "execute": "Nothing scheduled for this Saturday!",
        "comment": ">>> SAT SCHEDULE (PST) >>>              Magda Halina: The Vibe 4pm-7pm",
        "name": "saturday"
    },
    {
        "execute": "Nothing scheduled for this Sunday!",
        "comment": ">>> SUN SCHEDULE (PST) >>>              Rui Tokyo: The Unwind 4pm-7pm",
        "name": "sunday"
    },
    {
        "execute": "Come back next week to see what we have in store!",
        "coment": ">>> TOMORROW'S SCHEDULE (PST) >>>              Marie Vaunt 4pm, Alley Kay 5pm, Sian 6pm, Tyler Johnston: Into the Void 7pm, Idoru 8pm",
        "name": "tomorrow"
    }
]
