[
    {
        "execute": ">>> SCHEDULE (PST) >>>              The Reason Y 6pm, Idoru 7pm, Sian 8pm, Richey V & Simone Zino 9pm, Aardy 10pm",
        "name": "settimes"
    },
    {
        "execute": ">>> TUES SCHEDULE (PST) >>>              Michelle Sparks: Outside the Box (Hiroko Yamamura) 6pm, Speaker Honey: New Music Rundown 7pm, Juheun: In the Booth 8pm, Luke Andy x Freak On: Back and Forth 9pm, Kane x Rhyot: Demo Workshop 10pm",
        "name": "tuesday"
    },
    {
        "execute": ">>> WED SCHEDULE (PST) >>>              Mullen 6pm, Michelle Sparks 7pm, Juheun 8pm, Zeplin 9pm, Melody's Enemy 10pm",
        "name": "wednesday"
    },
    {
        "execute": ">>> THUR SCHEDULE (PST) >>>              The Reason Y 6pm, Idoru 7pm, Sian 8pm, Richey V & Simone Zino 9pm, Aardy 10pm",
        "name": "thursday"
    },
    {
        "execute": "Come back next week to see what we have in store!",
        "comment": ">>> TOMORROW'S SCHEDULE (PST) >>>              The Reason Y 6pm, Idoru 7pm, Sian 8pm, Richey V & Simone Zino 9pm, Aardy 10pm",
        "name": "tomorrow"
    }
]
